oslabnew/__init__.py
oslabnew/programs.py
oslabnew-0.0.4.dist-info/METADATA
oslabnew-0.0.4.dist-info/WHEEL
oslabnew-0.0.4.dist-info/top_level.txt
oslabnew-0.0.4.dist-info/RECORD
