Metadata-Version: 2.1
Name: oslabnew
Version: 0.0.4
Summary: A Python library with various useful OS code snippets.
Home-page: https://github.com/mdimado/oslabnew
Author: mdimado
Author-email: mdimad005@gmail.com
Classifier: Programming Language :: Python :: 3
Classifier: Operating System :: OS Independent
Requires-Python: >=3.6
